{
    "collectionName": "components_elements_cards",
    "info": {
      "displayName": "card",
      "description": ""
    },
    "options": {},
    "attributes": {
      "image": {
        "type": "media",
        "multiple": false,
        "required": false,
        "allowedTypes": ["images"]
      },
      "heading": {
        "type": "string"
      },
      "description": {
        "type": "text"
      },
      "duration": {
        "type": "string"
      },
      "link": {
        "type": "component",
        "repeatable": false,
        "component": "elements.buttom-link"
      },
      "category": {
        "type": "string",
        "required": false,
        "default": ""
      },
      "rating": {
        "type": "decimal",
        "required": false,
        "default": 0.0
      },
      "reviews": {
        "type": "integer",
        "required": false,
        "default": 0
      },
      "price": {
        "type": "decimal",
        "required": false,
        "default": 0.0
      },
      "slug": {
        "type": "uid",
        "targetField": "heading",
        "unique": true
      }
    }
  }
  